<?xml version="1.0"?>
<opencv_storage>
<stage7>
  <maxWeakCount>3</maxWeakCount>
  <stageThreshold>-8.0918979644775391e-01</stageThreshold>
  <weakClassifiers>
    <_>
      <internalNodes>
        0 -1 1186491 -1.3441074639558792e-02</internalNodes>
      <leafValues>
        5.8095240592956543e-01 -7.6237624883651733e-01</leafValues></_>
    <_>
      <internalNodes>
        0 -1 2567247 -4.5534563250839710e-03</internalNodes>
      <leafValues>
        5.1190775632858276e-01 -7.5408440828323364e-01</leafValues></_>
    <_>
      <internalNodes>
        0 -1 5044363 -4.8090452328324318e-03</internalNodes>
      <leafValues>
        8.0979257822036743e-01 -5.5872130393981934e-01</leafValues></_></weakClassifiers></stage7>
</opencv_storage>
